{"trial_id": "0021", "hyperparameters": {"space": [{"class_name": "Choice", "config": {"name": "activation", "default": "relu", "conditions": [], "values": ["relu", "tanh", "sigmoid"], "ordered": false}}, {"class_name": "Int", "config": {"name": "num_layers", "default": null, "conditions": [], "min_value": 1, "max_value": 3, "step": 1, "sampling": "linear"}}, {"class_name": "Int", "config": {"name": "layer0", "default": null, "conditions": [], "min_value": 30, "max_value": 240, "step": 30, "sampling": "linear"}}, {"class_name": "Choice", "config": {"name": "dropout0", "default": 0.0, "conditions": [], "values": [0.0, 0.01, 0.001, 0.0001], "ordered": true}}, {"class_name": "Choice", "config": {"name": "learning_rate", "default": 0.1, "conditions": [], "values": [0.1, 0.01, 0.001, 0.0001], "ordered": true}}, {"class_name": "Int", "config": {"name": "layer1", "default": null, "conditions": [], "min_value": 30, "max_value": 240, "step": 30, "sampling": "linear"}}, {"class_name": "Choice", "config": {"name": "dropout1", "default": 0.0, "conditions": [], "values": [0.0, 0.01, 0.001, 0.0001], "ordered": true}}, {"class_name": "Int", "config": {"name": "layer2", "default": null, "conditions": [], "min_value": 30, "max_value": 240, "step": 30, "sampling": "linear"}}, {"class_name": "Choice", "config": {"name": "dropout2", "default": 0.0, "conditions": [], "values": [0.0, 0.01, 0.001, 0.0001], "ordered": true}}], "values": {"activation": "relu", "num_layers": 1, "layer0": 120, "dropout0": 0.0, "learning_rate": 0.001, "layer1": 60, "dropout1": 0.01, "layer2": 30, "dropout2": 0.0, "tuner/epochs": 7, "tuner/initial_epoch": 0, "tuner/bracket": 1, "tuner/round": 0}}, "metrics": {"metrics": {"loss": {"direction": "min", "observations": [{"value": [80167739392.0], "step": 6}]}, "precision": {"direction": "min", "observations": [{"value": [0.6229971647262573], "step": 6}]}, "recall": {"direction": "min", "observations": [{"value": [0.6235849261283875], "step": 6}]}, "val_loss": {"direction": "min", "observations": [{"value": [307576704.0], "step": 6}]}, "val_precision": {"direction": "min", "observations": [{"value": [0.6233292818069458], "step": 6}]}, "val_recall": {"direction": "min", "observations": [{"value": [0.9570895433425903], "step": 6}]}, "lr": {"direction": "min", "observations": [{"value": [0.00970298983156681], "step": 6}]}}}, "score": 307576704.0, "best_step": 6, "status": "COMPLETED", "message": null}